networkscan/__init__.py
networkscan/networkscan.py
netscan_s7-1.0.4.dist-info/METADATA
netscan_s7-1.0.4.dist-info/WHEEL
netscan_s7-1.0.4.dist-info/entry_points.txt
netscan_s7-1.0.4.dist-info/top_level.txt
netscan_s7-1.0.4.dist-info/RECORD
