Metadata-Version: 2.4
Name: netscan-s7
Version: 1.0.4
Summary: A fast multi-threaded network port scanner
Author: SABIR7718
Classifier: Programming Language :: Python :: 3
Classifier: Operating System :: OS Independent
Requires-Python: >=3.7
Requires-Dist: colorama
Dynamic: author
Dynamic: classifier
Dynamic: requires-dist
Dynamic: requires-python
Dynamic: summary
